caesarcipher/__init__.py
caesarcipher/cipher.py
ebro_caesarcipher-0.1.2.dist-info/METADATA
ebro_caesarcipher-0.1.2.dist-info/WHEEL
ebro_caesarcipher-0.1.2.dist-info/top_level.txt
ebro_caesarcipher-0.1.2.dist-info/RECORD
