Metadata-Version: 2.4
Name: ebro_caesarcipher
Version: 0.1.2
Summary: A simple Python library that implements the Caesar cipher algorithm.
Author: Ebro1500
Dynamic: author
Dynamic: summary
